money_legos/__init__.py
money_legos/test.py
money_legos/util.py
money_legos/aave/__init__.py
money_legos/aave/contracts.py
money_legos/aave/abi/AToken.json
money_legos/aave/abi/LendingPool.json
money_legos/aave/abi/LendingPoolAddessProvider.json
money_legos/aave/abi/LendingPoolCore.json
money_legos/balancer/__init__.py
money_legos/balancer/contracts.py
money_legos/balancer/abi/BActions.json
money_legos/balancer/abi/BFactory.json
money_legos/balancer/abi/BPool.json
money_legos/balancer/abi/ExchangeProxy.json
money_legos/compound/__init__.py
money_legos/compound/contracts.py
money_legos/compound/abi/CEther.json
money_legos/compound/abi/CToken.json
money_legos/compound/abi/CompoundPriceOracle.json
money_legos/compound/abi/Comptroller.json
money_legos/curvefi/__init__.py
money_legos/curvefi/contracts.py
money_legos/curvefi/abi/Curve.json
money_legos/curvefi/abi/PoolToken.json
money_legos/curvefi/abi/Zap.json
money_legos/dappsys/__init__.py
money_legos/dappsys/contracts.py
money_legos/dappsys/abi/DSProxy.json
money_legos/dappsys/abi/DSProxyFactory.json
money_legos/dydx/__init__.py
money_legos/dydx/contracts.py
money_legos/dydx/abi/AdminImpl.json
money_legos/dydx/abi/CanonicalOrders.json
money_legos/dydx/abi/DaiPriceOracle.json
money_legos/dydx/abi/Expiry.json
money_legos/dydx/abi/ExpiryV2.json
money_legos/dydx/abi/LimitOrders.json
money_legos/dydx/abi/LiquidatorProxyV1ForSoloMargin.json
money_legos/dydx/abi/OperationImpl.json
money_legos/dydx/abi/PayableProxyForSoloMargin.json
money_legos/dydx/abi/PolynomialInterestSetter.json
money_legos/dydx/abi/Refunder.json
money_legos/dydx/abi/SaiPriceOracle.json
money_legos/dydx/abi/SignedOperationProxy.json
money_legos/dydx/abi/SoloMargin.json
money_legos/dydx/abi/StopLimitOrders.json
money_legos/dydx/abi/UsdcPriceOracle.json
money_legos/dydx/abi/WethPriceOracle.json
money_legos/erc20/__init__.py
money_legos/erc20/tokens.py
money_legos/erc20/abi/ERC20.json
money_legos/erc20/abi/WETH.json
money_legos/idle/__init__.py
py_money_legos-0.1.1.dist-info/LICENSE
py_money_legos-0.1.1.dist-info/METADATA
py_money_legos-0.1.1.dist-info/WHEEL
py_money_legos-0.1.1.dist-info/top_level.txt
py_money_legos-0.1.1.dist-info/RECORD
