Metadata-Version: 2.1
Name: py-money-legos
Version: 0.1.1
Summary: money-legos for Python
Home-page: https://github.com/gokhanbaydar/py-money-legos
Author: Gokhan Baydar
Author-email: gokhanbaydar@yahoo.com
License: UNKNOWN
Platform: UNKNOWN
Classifier: Programming Language :: Python :: 3
Classifier: License :: OSI Approved :: MIT License
Classifier: Operating System :: OS Independent
Requires-Python: >=3.6
